darkpyonix-0.1.0.dist-info/METADATA
darkpyonix-0.1.0.dist-info/WHEEL
darkpyonix-0.1.0.dist-info/entry_points.txt
darkpyonix-0.1.0.dist-info/licenses/LICENSE
darkpyonix/__init__.py
darkpyonix/__main__.py
darkpyonix/kernel/__init__.py
darkpyonix/kernel/__main__.py
darkpyonix/manager/app.py
darkpyonix-0.1.0.dist-info/RECORD
