Metadata-Version: 2.1
Name: darkpyonix
Version: 0.1.0
Summary: AI-optimized Python kernel with VS Code integration
Author-Email: Your Name <your.email@example.com>
License: MIT License
Requires-Python: >=3.9
Requires-Dist: fastapi>=0.116.1
Requires-Dist: uvicorn>=0.35.0
Provides-Extra: build
Requires-Dist: pdm>=2.25.5; extra == "build"
